dirtree_chart/__init__.py
dirtree_chart/__main__.py
dirtree_chart/config.py
dirtree_chart/diagram.py
dirtree_chart/utils/__init__.py
dirtree_chart/utils/helpers.py
dirtree_chart-0.0.6.dist-info/LICENSE
dirtree_chart-0.0.6.dist-info/METADATA
dirtree_chart-0.0.6.dist-info/WHEEL
dirtree_chart-0.0.6.dist-info/top_level.txt
dirtree_chart-0.0.6.dist-info/RECORD
