Metadata-Version: 2.1
Name: dirtree-chart
Version: 0.0.6
Summary: Directory structure diagram generator
Home-page: https://github.com/prayer007/dirtree-chart
Author: Manuel Strohmaier
Author-email: manuel.strohmaier@joanneum.at
License: UNKNOWN
Project-URL: Documentation, https://github.com/prayer007/dirtree-chart
Platform: UNKNOWN
Classifier: Programming Language :: Python :: 3
Classifier: License :: OSI Approved :: MIT License
Classifier: Operating System :: OS Independent
License-File: LICENSE
